[[["ee2f0ebf-84d4-45f9-a527-2b150e1ee5a3",{"pageContent":"Bulbasaur (Japanese: フシギダネ, Fushigidane) is a dual-type Grass/Poison Seed Pokémon and is the very","metadata":{"source":"./public/example.txt","loc":{"lines":{"from":1,"to":1}}}}],["c8f464fc-c158-4507-ab00-b6034fb444da",{"pageContent":"Grass/Poison Seed Pokémon and is the very first in the National Dex (#001). Standing at 0.7 meters","metadata":{"source":"./public/example.txt","loc":{"lines":{"from":1,"to":1}}}}],["dbd81d6c-a926-4736-9c75-b6fd9109e63f",{"pageContent":"the National Dex (#001). Standing at 0.7 meters and weighing 6.9 kg, Bulbasaur is known for being","metadata":{"source":"./public/example.txt","loc":{"lines":{"from":1,"to":1}}}}],["2653ca54-557a-493f-a317-b17ae3548499",{"pageContent":"and weighing 6.9 kg, Bulbasaur is known for being the only starter with dual types in its base","metadata":{"source":"./public/example.txt","loc":{"lines":{"from":1,"to":1}}}}],["c9e7c4fe-3213-4102-a418-c9796883f941",{"pageContent":"the only starter with dual types in its base form. It evolves into Ivysaur and later into Venusaur.","metadata":{"source":"./public/example.txt","loc":{"lines":{"from":1,"to":1}}}}],["98cd53ac-c58b-439e-9101-ae15d7453e92",{"pageContent":"It evolves into Ivysaur and later into Venusaur. Bulbasaur's abilities include Overgrow, with","metadata":{"source":"./public/example.txt","loc":{"lines":{"from":1,"to":1}}}}],["58770014-046d-4cf5-864a-640c2ad32e6c",{"pageContent":"Bulbasaur's abilities include Overgrow, with Chlorophyll as its hidden ability. It debuted as a","metadata":{"source":"./public/example.txt","loc":{"lines":{"from":1,"to":1}}}}],["8f3eaa8c-ba8c-4d74-8628-f2e81dfb5315",{"pageContent":"as its hidden ability. It debuted as a starter in Pokémon Red, Blue, and Green. In battles,","metadata":{"source":"./public/example.txt","loc":{"lines":{"from":1,"to":1}}}}],["4e3e7e88-7992-4c2e-a085-3cd1faf16479",{"pageContent":"in Pokémon Red, Blue, and Green. In battles, Bulbasaur can learn moves like Leech Seed and Sleep","metadata":{"source":"./public/example.txt","loc":{"lines":{"from":1,"to":1}}}}],["d9bfa233-3841-4742-b61b-29f6490ff671",{"pageContent":"can learn moves like Leech Seed and Sleep Powder, making it a solid tactical choice. In competitive","metadata":{"source":"./public/example.txt","loc":{"lines":{"from":1,"to":1}}}}],["5606ce9c-120e-4573-b3fb-6cb3b4e2d175",{"pageContent":"making it a solid tactical choice. In competitive Little Cup play, it becomes surprisingly tanky","metadata":{"source":"./public/example.txt","loc":{"lines":{"from":1,"to":1}}}}],["b1a7521b-4b9a-4abb-a237-3231f552e130",{"pageContent":"Little Cup play, it becomes surprisingly tanky with an Eviolite, using Sleep Powder, Leech Seed,","metadata":{"source":"./public/example.txt","loc":{"lines":{"from":1,"to":1}}}}],["bc771629-e6da-44f6-9cf7-2ae2ad4b9c6e",{"pageContent":"with an Eviolite, using Sleep Powder, Leech Seed, and Sludge Bomb to great effect.","metadata":{"source":"./public/example.txt","loc":{"lines":{"from":1,"to":1}}}}],["d69e8625-d9b8-4c35-a10c-629976c7d04c",{"pageContent":"Ivysaur (Japanese: フシギソウ, Fushigisou) evolves from Bulbasaur and continues the Grass/Poison typing.","metadata":{"source":"./public/example.txt","loc":{"lines":{"from":3,"to":3}}}}],["485373a7-6373-4704-b19a-0c566c55825d",{"pageContent":"Bulbasaur and continues the Grass/Poison typing. Registered as #002 in the National Dex, Ivysaur","metadata":{"source":"./public/example.txt","loc":{"lines":{"from":3,"to":3}}}}],["67380e4d-2481-4989-8a85-41499176105d",{"pageContent":"Registered as #002 in the National Dex, Ivysaur stands at 1.0 meter and weighs 13.0 kg. Its","metadata":{"source":"./public/example.txt","loc":{"lines":{"from":3,"to":3}}}}],["cb87e7b7-406b-4201-b0ce-d0d7efa51f55",{"pageContent":"stands at 1.0 meter and weighs 13.0 kg. Its distinctive flower bud on its back grows larger with","metadata":{"source":"./public/example.txt","loc":{"lines":{"from":3,"to":3}}}}],["46c16bf4-3691-43f7-a62e-e385e99fee1f",{"pageContent":"flower bud on its back grows larger with more sunlight exposure. Ivysaur shares the same abilities","metadata":{"source":"./public/example.txt","loc":{"lines":{"from":3,"to":3}}}}],["aa34998f-edc3-4eb0-92c7-ccef1358b122",{"pageContent":"exposure. Ivysaur shares the same abilities as Bulbasaur—Overgrow and Chlorophyll (hidden). In","metadata":{"source":"./public/example.txt","loc":{"lines":{"from":3,"to":3}}}}],["b5111459-f883-4888-b194-27739b1d7939",{"pageContent":"Bulbasaur—Overgrow and Chlorophyll (hidden). In lower-tier competitive formats, Ivysaur performs","metadata":{"source":"./public/example.txt","loc":{"lines":{"from":3,"to":3}}}}],["ec7b1ec3-45ef-457b-9a9a-28ab381bf781",{"pageContent":"lower-tier competitive formats, Ivysaur performs well with Eviolite, utilizing Giga Drain and Knock","metadata":{"source":"./public/example.txt","loc":{"lines":{"from":3,"to":3}}}}],["904fcd2f-9345-492c-b1a2-670ada8ba101",{"pageContent":"with Eviolite, utilizing Giga Drain and Knock Off for both bulk and utility.","metadata":{"source":"./public/example.txt","loc":{"lines":{"from":3,"to":3}}}}],["2e6e330d-f9fc-46aa-9190-58196b1151cc",{"pageContent":"Venusaur (Japanese: フシギバナ, Fushigibana), the final evolution of Bulbasaur, is a Grass/Poison","metadata":{"source":"./public/example.txt","loc":{"lines":{"from":5,"to":5}}}}],["5641a649-09cf-4f88-96d4-ee3cfdb2d06f",{"pageContent":"final evolution of Bulbasaur, is a Grass/Poison Pokémon listed as #003. It grows to 2.0 meters in","metadata":{"source":"./public/example.txt","loc":{"lines":{"from":5,"to":5}}}}],["0b5c095b-6d05-48aa-a874-d342efede141",{"pageContent":"Pokémon listed as #003. It grows to 2.0 meters in height and weighs 100.0 kg. Venusaur has a Mega","metadata":{"source":"./public/example.txt","loc":{"lines":{"from":5,"to":5}}}}],["c040a4e5-357e-46ee-906d-82a8847470c8",{"pageContent":"height and weighs 100.0 kg. Venusaur has a Mega Evolution and can also Gigantamax in Sword and","metadata":{"source":"./public/example.txt","loc":{"lines":{"from":5,"to":5}}}}],["0d081088-2236-4ee3-96f9-3653d117c465",{"pageContent":"Evolution and can also Gigantamax in Sword and Shield. Its abilities include Overgrow, with Thick","metadata":{"source":"./public/example.txt","loc":{"lines":{"from":5,"to":5}}}}],["78dbd354-a497-43f7-94b6-1da7171e04ec",{"pageContent":"Its abilities include Overgrow, with Thick Fat as a Mega ability, giving it resistance to Fire and","metadata":{"source":"./public/example.txt","loc":{"lines":{"from":5,"to":5}}}}],["be2ecb33-c055-4202-a5e5-50f5a0e70fca",{"pageContent":"a Mega ability, giving it resistance to Fire and Ice attacks. Venusaur is often depicted absorbing","metadata":{"source":"./public/example.txt","loc":{"lines":{"from":5,"to":5}}}}],["450d860f-81df-4d2e-87d8-453edaa6dfc9",{"pageContent":"Ice attacks. Venusaur is often depicted absorbing sunlight through the large flower on its back.","metadata":{"source":"./public/example.txt","loc":{"lines":{"from":5,"to":5}}}}],["e25145ab-8351-4d65-ad78-432aa2f146cb",{"pageContent":"sunlight through the large flower on its back. Competitively, Mega Venusaur thrives in the OU tier,","metadata":{"source":"./public/example.txt","loc":{"lines":{"from":5,"to":5}}}}],["e6750518-1e25-4e0e-a0a9-a583f3139afb",{"pageContent":"Mega Venusaur thrives in the OU tier, especially with a moveset like Giga Drain, Sludge Bomb,","metadata":{"source":"./public/example.txt","loc":{"lines":{"from":5,"to":5}}}}],["40eb4399-f758-4132-9e95-fa7eab7f2d17",{"pageContent":"with a moveset like Giga Drain, Sludge Bomb, Synthesis, and Leech Seed, making it both durable and","metadata":{"source":"./public/example.txt","loc":{"lines":{"from":5,"to":5}}}}],["29b1b6d8-3d67-46d8-ba95-326e239de102",{"pageContent":"and Leech Seed, making it both durable and threatening.","metadata":{"source":"./public/example.txt","loc":{"lines":{"from":5,"to":5}}}}],["b2c58be2-4fad-47e6-9882-ed4af5746ba9",{"pageContent":"Charmander (Japanese: ヒトカゲ, Hitokage) is a Fire-type Lizard Pokémon and appears as #004 in the","metadata":{"source":"./public/example.txt","loc":{"lines":{"from":7,"to":7}}}}],["10ac621d-3683-4c1d-a57a-b587c2c63eda",{"pageContent":"Lizard Pokémon and appears as #004 in the National Dex. It stands at 0.6 meters and weighs 8.5 kg.","metadata":{"source":"./public/example.txt","loc":{"lines":{"from":7,"to":7}}}}],["ea36bacf-c8c4-4f79-9288-60f37c1ff28d",{"pageContent":"Dex. It stands at 0.6 meters and weighs 8.5 kg. Known for the flame on its tail that reflects its","metadata":{"source":"./public/example.txt","loc":{"lines":{"from":7,"to":7}}}}],["b3a62987-ce8c-4f52-ae6a-b6be4544b8df",{"pageContent":"Known for the flame on its tail that reflects its emotional state, Charmander evolves into","metadata":{"source":"./public/example.txt","loc":{"lines":{"from":7,"to":7}}}}],["089384a7-f3d0-49e3-9df5-cd545c927a76",{"pageContent":"its emotional state, Charmander evolves into Charmeleon and then Charizard. Its abilities include","metadata":{"source":"./public/example.txt","loc":{"lines":{"from":7,"to":7}}}}],["4d5cfe23-6943-4df4-936d-c5295eeba6ed",{"pageContent":"and then Charizard. Its abilities include Blaze and Solar Power as its hidden ability. In","metadata":{"source":"./public/example.txt","loc":{"lines":{"from":7,"to":7}}}}],["46bfc6dc-c451-4373-a3fd-6512f4cd257c",{"pageContent":"Blaze and Solar Power as its hidden ability. In competitive Little Cup battles, Charmander can deal","metadata":{"source":"./public/example.txt","loc":{"lines":{"from":7,"to":7}}}}],["6c4fc8f3-25a3-49e3-be91-5d9291df31dd",{"pageContent":"Little Cup battles, Charmander can deal significant damage under sunlight using Solar Power and","metadata":{"source":"./public/example.txt","loc":{"lines":{"from":7,"to":7}}}}],["0b202c6a-7393-4a79-a0e0-77b47de9ae9e",{"pageContent":"damage under sunlight using Solar Power and Fire Blast.","metadata":{"source":"./public/example.txt","loc":{"lines":{"from":7,"to":7}}}}],["342767d6-b42d-447e-83e5-cf2b545754d8",{"pageContent":"Charmeleon (Japanese: リザード, Lizardo) is the evolved form of Charmander and maintains the Fire","metadata":{"source":"./public/example.txt","loc":{"lines":{"from":9,"to":9}}}}],["2a49493c-e564-4b51-bb41-165c16787fa5",{"pageContent":"evolved form of Charmander and maintains the Fire typing. Listed as #005 in the National Dex,","metadata":{"source":"./public/example.txt","loc":{"lines":{"from":9,"to":9}}}}],["596f14df-f64b-4067-86fa-52545a520c11",{"pageContent":"Fire typing. Listed as #005 in the National Dex, Charmeleon is 1.1 meters tall and weighs 19.0 kg.","metadata":{"source":"./public/example.txt","loc":{"lines":{"from":9,"to":9}}}}],["d2d53546-f494-426e-818a-639a43eed5e3",{"pageContent":"Charmeleon is 1.1 meters tall and weighs 19.0 kg. It has a fierce personality and is known for its","metadata":{"source":"./public/example.txt","loc":{"lines":{"from":9,"to":9}}}}],["771cec49-7ad1-4a0f-9274-a0d0885dca2f",{"pageContent":"It has a fierce personality and is known for its aggressive nature in battle. With Blaze and Solar","metadata":{"source":"./public/example.txt","loc":{"lines":{"from":9,"to":9}}}}],["0b8bc81e-2d8c-4676-b166-3c5307b6b4e7",{"pageContent":"aggressive nature in battle. With Blaze and Solar Power abilities, it can serve as a special","metadata":{"source":"./public/example.txt","loc":{"lines":{"from":9,"to":9}}}}],["b63ee887-f088-419b-9c9f-eb7a6b7f5b29",{"pageContent":"Solar Power abilities, it can serve as a special attacker in mid-tier formats. Equipping Eviolite","metadata":{"source":"./public/example.txt","loc":{"lines":{"from":9,"to":9}}}}],["4c746885-169c-439d-aefc-0facfe786693",{"pageContent":"attacker in mid-tier formats. Equipping Eviolite enhances its survivability, and it can use moves","metadata":{"source":"./public/example.txt","loc":{"lines":{"from":9,"to":9}}}}],["24d161cf-6159-4ed3-acd2-d27c7419e6ed",{"pageContent":"enhances its survivability, and it can use moves like Fire Blast, Dragon Pulse, and Sunny Day for","metadata":{"source":"./public/example.txt","loc":{"lines":{"from":9,"to":9}}}}],["af3b571c-804b-4a81-8c7e-2f3bd3e2640b",{"pageContent":"like Fire Blast, Dragon Pulse, and Sunny Day for offensive setups.","metadata":{"source":"./public/example.txt","loc":{"lines":{"from":9,"to":9}}}}],["a84507b0-d8b8-4eb7-8a90-3083b3f9cae6",{"pageContent":"Charizard (Japanese: リザードン, Lizardon), the final evolution of Charmander, is a Fire/Flying-type","metadata":{"source":"./public/example.txt","loc":{"lines":{"from":11,"to":11}}}}],["31bfa9fc-109d-4b10-a6d0-f6f4a124ddf3",{"pageContent":"evolution of Charmander, is a Fire/Flying-type Pokémon. It’s #006 in the National Dex, with a","metadata":{"source":"./public/example.txt","loc":{"lines":{"from":11,"to":11}}}}],["f548a1ae-ea5b-4165-b2ae-cca35e7b1446",{"pageContent":"Pokémon. It’s #006 in the National Dex, with a height of 1.7 meters and weight of 90.5 kg.","metadata":{"source":"./public/example.txt","loc":{"lines":{"from":11,"to":11}}}}],["b2319473-b5f1-448a-abc3-9a577f0ef929",{"pageContent":"a height of 1.7 meters and weight of 90.5 kg. Charizard has both Mega Evolutions (X and Y) and a","metadata":{"source":"./public/example.txt","loc":{"lines":{"from":11,"to":11}}}}],["c5e201a3-6eb5-49fd-bca5-1e005f870eac",{"pageContent":"has both Mega Evolutions (X and Y) and a Gigantamax form. Its abilities vary: Blaze is standard,","metadata":{"source":"./public/example.txt","loc":{"lines":{"from":11,"to":11}}}}],["f38b36f2-add4-4423-8f16-de6de7dfd767",{"pageContent":"form. Its abilities vary: Blaze is standard, Tough Claws for Mega X, and Drought for Mega Y.","metadata":{"source":"./public/example.txt","loc":{"lines":{"from":11,"to":11}}}}],["1c63902e-5793-4d8e-aa6c-b74da36e5aa7",{"pageContent":"Tough Claws for Mega X, and Drought for Mega Y. Notably, Mega Charizard X gains the Dragon typing.","metadata":{"source":"./public/example.txt","loc":{"lines":{"from":11,"to":11}}}}],["587f7727-5f2c-4723-b411-ae3d62a5da5d",{"pageContent":"Mega Charizard X gains the Dragon typing. It’s extremely popular in the anime and merchandise.","metadata":{"source":"./public/example.txt","loc":{"lines":{"from":11,"to":11}}}}],["7d5b9414-6e10-4532-8bfc-1e3cff580e91",{"pageContent":"extremely popular in the anime and merchandise. Competitively, Mega Charizard Y is a great sun team","metadata":{"source":"./public/example.txt","loc":{"lines":{"from":11,"to":11}}}}],["f6e9326b-1738-40e1-8b5c-ad30e9b2a783",{"pageContent":"Mega Charizard Y is a great sun team leader using Drought, Fire Blast, and Solar Beam. Mega","metadata":{"source":"./public/example.txt","loc":{"lines":{"from":11,"to":11}}}}],["f015267a-4631-4307-9651-ebc6cedff927",{"pageContent":"using Drought, Fire Blast, and Solar Beam. Mega Charizard X focuses on physical offense with Dragon","metadata":{"source":"./public/example.txt","loc":{"lines":{"from":11,"to":11}}}}],["ba7161a6-48dd-4bde-9598-446c2689e0d1",{"pageContent":"X focuses on physical offense with Dragon Dance, Flare Blitz, and Dragon Claw. The Gigantamax form","metadata":{"source":"./public/example.txt","loc":{"lines":{"from":11,"to":11}}}}],["22a5311b-33cb-44fd-9ade-f6582c653f54",{"pageContent":"Flare Blitz, and Dragon Claw. The Gigantamax form excels in Dynamax formats with G-Max Wildfire.","metadata":{"source":"./public/example.txt","loc":{"lines":{"from":11,"to":11}}}}],["51f4cb02-110d-48a1-aa3b-d93536d56038",{"pageContent":"Squirtle (Japanese: ゼニガメ, Zenigame) is a Water-type Tiny Turtle Pokémon and starts the Squirtle","metadata":{"source":"./public/example.txt","loc":{"lines":{"from":13,"to":13}}}}],["7dc80e5d-c6d3-4564-803a-2df22efdc781",{"pageContent":"Tiny Turtle Pokémon and starts the Squirtle evolution line. It is #007 in the National Dex, stands","metadata":{"source":"./public/example.txt","loc":{"lines":{"from":13,"to":13}}}}],["2b6fb71c-7647-4456-85b5-4407e5d18d1f",{"pageContent":"line. It is #007 in the National Dex, stands 0.5 meters tall, and weighs 9.0 kg. With Torrent and","metadata":{"source":"./public/example.txt","loc":{"lines":{"from":13,"to":13}}}}],["b1b473d1-16fa-4e22-b9b7-bda5d2e8442a",{"pageContent":"meters tall, and weighs 9.0 kg. With Torrent and Rain Dish (hidden ability), Squirtle can become","metadata":{"source":"./public/example.txt","loc":{"lines":{"from":13,"to":13}}}}],["f06b4d03-3fa9-4f63-8505-fdae36492dee",{"pageContent":"Rain Dish (hidden ability), Squirtle can become quite the threat in Little Cup battles. In the","metadata":{"source":"./public/example.txt","loc":{"lines":{"from":13,"to":13}}}}],["11dd831b-22a5-4379-afb4-dc544e927834",{"pageContent":"quite the threat in Little Cup battles. In the anime, it famously led the 'Squirtle Squad'.","metadata":{"source":"./public/example.txt","loc":{"lines":{"from":13,"to":13}}}}],["41d93ca0-bc17-4ea5-94fa-b6e4e85f0755",{"pageContent":"the anime, it famously led the 'Squirtle Squad'. Competitively, its Shell Smash set is dangerous,","metadata":{"source":"./public/example.txt","loc":{"lines":{"from":13,"to":13}}}}],["0e0562bc-5e92-483e-afde-5ec3efc7846f",{"pageContent":"Competitively, its Shell Smash set is dangerous, allowing powerful moves like Hydro Pump and Ice","metadata":{"source":"./public/example.txt","loc":{"lines":{"from":13,"to":13}}}}],["80957533-bb07-40a7-8101-cadf23127255",{"pageContent":"allowing powerful moves like Hydro Pump and Ice Beam to shine.","metadata":{"source":"./public/example.txt","loc":{"lines":{"from":13,"to":13}}}}],["5129a4b3-ff6a-4b55-90c2-46aa08469255",{"pageContent":"Wartortle (Japanese: カメール, Kameil) evolves from Squirtle and is also a Water-type Pokémon. Number","metadata":{"source":"./public/example.txt","loc":{"lines":{"from":15,"to":15}}}}],["afa5de11-abff-4c2f-b83f-e733309c189b",{"pageContent":"Squirtle and is also a Water-type Pokémon. Number #008 in the National Dex, it grows to 1.0 meter","metadata":{"source":"./public/example.txt","loc":{"lines":{"from":15,"to":15}}}}],["7934e5fa-5228-49fd-be81-8b24a2d53925",{"pageContent":"#008 in the National Dex, it grows to 1.0 meter and weighs 22.5 kg. Its fluffy tail is a symbol of","metadata":{"source":"./public/example.txt","loc":{"lines":{"from":15,"to":15}}}}],["b6fb3bf0-968e-493e-81b1-1c6ef98dd4ba",{"pageContent":"weighs 22.5 kg. Its fluffy tail is a symbol of age and wisdom. It shares Torrent and Rain Dish as","metadata":{"source":"./public/example.txt","loc":{"lines":{"from":15,"to":15}}}}],["569d309f-6944-4094-90a4-e37c492f439e",{"pageContent":"and wisdom. It shares Torrent and Rain Dish as abilities. In competitive play, Wartortle is valued","metadata":{"source":"./public/example.txt","loc":{"lines":{"from":15,"to":15}}}}],["005f96e7-ed11-48ba-babb-230efff81123",{"pageContent":"In competitive play, Wartortle is valued as a defensive support with Eviolite, using Rapid Spin,","metadata":{"source":"./public/example.txt","loc":{"lines":{"from":15,"to":15}}}}],["2c8cf0df-35f4-47c6-8ed0-49a491b51534",{"pageContent":"support with Eviolite, using Rapid Spin, Scald, and Haze to maintain control on the field.","metadata":{"source":"./public/example.txt","loc":{"lines":{"from":15,"to":15}}}}],["f901921f-fa9a-4080-849a-9c99a82cd7ff",{"pageContent":"Blastoise (Japanese: カメックス, Kamex) is the final evolution of Squirtle and a pure Water-type","metadata":{"source":"./public/example.txt","loc":{"lines":{"from":17,"to":17}}}}],["55c49d90-43de-4950-98d2-15405c8407d5",{"pageContent":"final evolution of Squirtle and a pure Water-type Pokémon. At 1.6 meters tall and weighing 85.5 kg,","metadata":{"source":"./public/example.txt","loc":{"lines":{"from":17,"to":17}}}}],["08fa314c-9c03-48a7-bb4b-3ec53b49bc78",{"pageContent":"Pokémon. At 1.6 meters tall and weighing 85.5 kg, it is #009 in the National Dex. Blastoise has","metadata":{"source":"./public/example.txt","loc":{"lines":{"from":17,"to":17}}}}],["8c5d0e4a-cb5f-4183-aca6-70fc959e6c62",{"pageContent":"kg, it is #009 in the National Dex. Blastoise has both a Mega Evolution and a Gigantamax form. Its","metadata":{"source":"./public/example.txt","loc":{"lines":{"from":17,"to":17}}}}],["06877b19-5c27-4f64-b246-c57e232a788d",{"pageContent":"both a Mega Evolution and a Gigantamax form. Its abilities include Torrent and Mega Launcher","metadata":{"source":"./public/example.txt","loc":{"lines":{"from":17,"to":17}}}}],["749bfdb9-0c37-4d48-b398-53a5ce18aea7",{"pageContent":"Its abilities include Torrent and Mega Launcher (Mega). Known for the powerful water cannons on its","metadata":{"source":"./public/example.txt","loc":{"lines":{"from":17,"to":17}}}}],["050ffc9e-4d0c-4ad3-ac88-e2bd773c405c",{"pageContent":"Known for the powerful water cannons on its back, Blastoise becomes a formidable attacker in its","metadata":{"source":"./public/example.txt","loc":{"lines":{"from":17,"to":17}}}}],["2bf0fd90-b01f-4fd8-be58-2305b3062fe1",{"pageContent":"Blastoise becomes a formidable attacker in its Mega form. It benefits from Mega Launcher, boosting","metadata":{"source":"./public/example.txt","loc":{"lines":{"from":17,"to":17}}}}],["f4102755-c4a6-45c9-b39e-d53cf60393ad",{"pageContent":"form. It benefits from Mega Launcher, boosting moves like Aura Sphere, Dark Pulse, and Water Pulse,","metadata":{"source":"./public/example.txt","loc":{"lines":{"from":17,"to":17}}}}],["64b2f859-f96a-46bc-a266-1825c1d58852",{"pageContent":"like Aura Sphere, Dark Pulse, and Water Pulse, and it serves as an excellent Rapid Spinner in the","metadata":{"source":"./public/example.txt","loc":{"lines":{"from":17,"to":17}}}}],["ef75bbb5-53c7-45a5-bb02-eba604e56e4a",{"pageContent":"it serves as an excellent Rapid Spinner in the OU tier.","metadata":{"source":"./public/example.txt","loc":{"lines":{"from":17,"to":17}}}}]],{"0":"ee2f0ebf-84d4-45f9-a527-2b150e1ee5a3","1":"c8f464fc-c158-4507-ab00-b6034fb444da","2":"dbd81d6c-a926-4736-9c75-b6fd9109e63f","3":"2653ca54-557a-493f-a317-b17ae3548499","4":"c9e7c4fe-3213-4102-a418-c9796883f941","5":"98cd53ac-c58b-439e-9101-ae15d7453e92","6":"58770014-046d-4cf5-864a-640c2ad32e6c","7":"8f3eaa8c-ba8c-4d74-8628-f2e81dfb5315","8":"4e3e7e88-7992-4c2e-a085-3cd1faf16479","9":"d9bfa233-3841-4742-b61b-29f6490ff671","10":"5606ce9c-120e-4573-b3fb-6cb3b4e2d175","11":"b1a7521b-4b9a-4abb-a237-3231f552e130","12":"bc771629-e6da-44f6-9cf7-2ae2ad4b9c6e","13":"d69e8625-d9b8-4c35-a10c-629976c7d04c","14":"485373a7-6373-4704-b19a-0c566c55825d","15":"67380e4d-2481-4989-8a85-41499176105d","16":"cb87e7b7-406b-4201-b0ce-d0d7efa51f55","17":"46c16bf4-3691-43f7-a62e-e385e99fee1f","18":"aa34998f-edc3-4eb0-92c7-ccef1358b122","19":"b5111459-f883-4888-b194-27739b1d7939","20":"ec7b1ec3-45ef-457b-9a9a-28ab381bf781","21":"904fcd2f-9345-492c-b1a2-670ada8ba101","22":"2e6e330d-f9fc-46aa-9190-58196b1151cc","23":"5641a649-09cf-4f88-96d4-ee3cfdb2d06f","24":"0b5c095b-6d05-48aa-a874-d342efede141","25":"c040a4e5-357e-46ee-906d-82a8847470c8","26":"0d081088-2236-4ee3-96f9-3653d117c465","27":"78dbd354-a497-43f7-94b6-1da7171e04ec","28":"be2ecb33-c055-4202-a5e5-50f5a0e70fca","29":"450d860f-81df-4d2e-87d8-453edaa6dfc9","30":"e25145ab-8351-4d65-ad78-432aa2f146cb","31":"e6750518-1e25-4e0e-a0a9-a583f3139afb","32":"40eb4399-f758-4132-9e95-fa7eab7f2d17","33":"29b1b6d8-3d67-46d8-ba95-326e239de102","34":"b2c58be2-4fad-47e6-9882-ed4af5746ba9","35":"10ac621d-3683-4c1d-a57a-b587c2c63eda","36":"ea36bacf-c8c4-4f79-9288-60f37c1ff28d","37":"b3a62987-ce8c-4f52-ae6a-b6be4544b8df","38":"089384a7-f3d0-49e3-9df5-cd545c927a76","39":"4d5cfe23-6943-4df4-936d-c5295eeba6ed","40":"46bfc6dc-c451-4373-a3fd-6512f4cd257c","41":"6c4fc8f3-25a3-49e3-be91-5d9291df31dd","42":"0b202c6a-7393-4a79-a0e0-77b47de9ae9e","43":"342767d6-b42d-447e-83e5-cf2b545754d8","44":"2a49493c-e564-4b51-bb41-165c16787fa5","45":"596f14df-f64b-4067-86fa-52545a520c11","46":"d2d53546-f494-426e-818a-639a43eed5e3","47":"771cec49-7ad1-4a0f-9274-a0d0885dca2f","48":"0b8bc81e-2d8c-4676-b166-3c5307b6b4e7","49":"b63ee887-f088-419b-9c9f-eb7a6b7f5b29","50":"4c746885-169c-439d-aefc-0facfe786693","51":"24d161cf-6159-4ed3-acd2-d27c7419e6ed","52":"af3b571c-804b-4a81-8c7e-2f3bd3e2640b","53":"a84507b0-d8b8-4eb7-8a90-3083b3f9cae6","54":"31bfa9fc-109d-4b10-a6d0-f6f4a124ddf3","55":"f548a1ae-ea5b-4165-b2ae-cca35e7b1446","56":"b2319473-b5f1-448a-abc3-9a577f0ef929","57":"c5e201a3-6eb5-49fd-bca5-1e005f870eac","58":"f38b36f2-add4-4423-8f16-de6de7dfd767","59":"1c63902e-5793-4d8e-aa6c-b74da36e5aa7","60":"587f7727-5f2c-4723-b411-ae3d62a5da5d","61":"7d5b9414-6e10-4532-8bfc-1e3cff580e91","62":"f6e9326b-1738-40e1-8b5c-ad30e9b2a783","63":"f015267a-4631-4307-9651-ebc6cedff927","64":"ba7161a6-48dd-4bde-9598-446c2689e0d1","65":"22a5311b-33cb-44fd-9ade-f6582c653f54","66":"51f4cb02-110d-48a1-aa3b-d93536d56038","67":"7dc80e5d-c6d3-4564-803a-2df22efdc781","68":"2b6fb71c-7647-4456-85b5-4407e5d18d1f","69":"b1b473d1-16fa-4e22-b9b7-bda5d2e8442a","70":"f06b4d03-3fa9-4f63-8505-fdae36492dee","71":"11dd831b-22a5-4379-afb4-dc544e927834","72":"41d93ca0-bc17-4ea5-94fa-b6e4e85f0755","73":"0e0562bc-5e92-483e-afde-5ec3efc7846f","74":"80957533-bb07-40a7-8101-cadf23127255","75":"5129a4b3-ff6a-4b55-90c2-46aa08469255","76":"afa5de11-abff-4c2f-b83f-e733309c189b","77":"7934e5fa-5228-49fd-be81-8b24a2d53925","78":"b6fb3bf0-968e-493e-81b1-1c6ef98dd4ba","79":"569d309f-6944-4094-90a4-e37c492f439e","80":"005f96e7-ed11-48ba-babb-230efff81123","81":"2c8cf0df-35f4-47c6-8ed0-49a491b51534","82":"f901921f-fa9a-4080-849a-9c99a82cd7ff","83":"55c49d90-43de-4950-98d2-15405c8407d5","84":"08fa314c-9c03-48a7-bb4b-3ec53b49bc78","85":"8c5d0e4a-cb5f-4183-aca6-70fc959e6c62","86":"06877b19-5c27-4f64-b246-c57e232a788d","87":"749bfdb9-0c37-4d48-b398-53a5ce18aea7","88":"050ffc9e-4d0c-4ad3-ac88-e2bd773c405c","89":"2bf0fd90-b01f-4fd8-be58-2305b3062fe1","90":"f4102755-c4a6-45c9-b39e-d53cf60393ad","91":"64b2f859-f96a-46bc-a266-1825c1d58852","92":"ef75bbb5-53c7-45a5-bb02-eba604e56e4a"}]